[
    {
        "uid": 1,
        "title": "Learn Angular 2.0",
        "notes": "checkout the basics of AtScript and ECMA Script 6",
        "status": false
    },
    {
        "uid": 2,
        "title": "Explore Angular Material",
        "notes": "follow: http://material.angular.org/",
        "status": false
    },
    {
        "uid": 3,
        "title": "POC on Polymer",
        "notes": "follow the example on offical site: http://polymer-project.org/",
        "status": false
    },
    {
        "uid": 4,
        "title": "Document study on Polymer",
        "notes": "Create a Google Doc and share",
        "status": false
    }
    
]
